jointbox_cli/__init__.py
jointbox_cli/__version__.py
jointbox_cli/cli.py
jointbox_cli/const.py
jointbox_cli/core.py
jointbox_cli/helper.py
jointbox_cli/pipeline.py
jointbox_cli/scaffold.py
jointbox_cli/schema.py
jointbox_cli/secrets.py
jointbox_cli/validate.py
jointbox_cli/yaml_tools.py
jointbox_cli/esphome_ext/__init__.py
jointbox_cli/esphome_ext/expressions/__init__.py
jointbox_cli/esphome_ext/expressions/common.py
jointbox_cli/esphome_ext/expressions/const.py
jointbox_cli/esphome_ext/expressions/control_structures.py
jointbox_cli/esphome_ext/expressions/core.py
jointbox_cli/esphome_ext/expressions/filters.py
jointbox_cli/esphome_ext/packages/__init__.py
jointbox_cli/esphome_ext/packages/common.py
jointbox_cli/esphome_ext/packages/const.py
jointbox_cli/esphome_ext/packages/core.py
jointbox_cli/esphome_ext/packages/loader.py
jointbox_cli/esphome_ext/packages/validation.py
jointbox_cli/esphome_ext/packages/resources/jbstd/main.yaml
jointbox_cli/esphome_ext/repositories/__init__.py
jointbox-0.3.5.dist-info/METADATA
jointbox-0.3.5.dist-info/WHEEL
jointbox-0.3.5.dist-info/entry_points.txt
jointbox-0.3.5.dist-info/top_level.txt
jointbox-0.3.5.dist-info/RECORD
