Metadata-Version: 2.1
Name: jointbox
Version: 0.3.5
Summary: Jointbox - a toolchain for managing JointBox devices
Home-page: https://github.com/jointbox/jointbox-cli
Author: Jointbox
License: GPL-3.0-or-later
Keywords: python cli iot smarthome homeassistant esphome
Platform: UNKNOWN
Classifier: Development Status :: 3 - Alpha
Classifier: Intended Audience :: Developers
Classifier: Topic :: Software Development :: Libraries :: Python Modules
Classifier: Topic :: Home Automation
Classifier: License :: OSI Approved :: GNU General Public License v3 or later (GPLv3+)
Classifier: Programming Language :: Python :: 3
Classifier: Programming Language :: Python :: 3.6
Classifier: Programming Language :: Python :: 3.7
Classifier: Programming Language :: Python :: 3.8
Classifier: Programming Language :: Python :: 3.9
Requires-Python: >3.6
Requires-Dist: strome (~=1.0.0)
